[
  {
    "url": "https://manhwa18.cc/",
    "searchUrl": "https://manhwa18.cc/search?q=${search}&page=${page}",
    "type": "4",
    "NSFW": "1",
    "isEmbed": "0",
    "name": "manhwa18",
    "icon": "https://manhwa18.cc/images/manhwa18.png",
    "query": {
      "latest": "webtoons/{page}?orderby=latest",
      "popular": "webtoons/{page}?orderby=trending",
      "rating": "webtoons/{page}?orderby=rating"
    },
    "config": {
      "title_selector": {
        "selector": ".bsx >  .thumb > a",
        "attribute": "title"
      },
      "thumbnail_selector": {
        "selector": ".bsx >  .thumb > a   >  img",
        "attribute": "data-src"
      },
      "content_url_selector": {
        "selector": ".bsx >  .thumb > a",
        "attribute": "href"
      },
      "detail_selector": {
        "selector": "html"
      },
      "detail": {
        "discription_selector": {
          "selector": "meta[name='description']",
          "attribute": "content"
        },
        "genre_selector": {
          "selector": ".post-status > .post-content_item:last-child > .summary-content"
        },
        "status_selector": {
          "selector": ".post-status > .post-content_item:last-child > .summary-content"
        },
        "chapter_name_selector": {
          "selector": "a"
        },
        "chapter_image_selector": {
          "selector": ""
        },
        "chapters_selector": {
          "selector": "#chapterlist > .row-content-chapter > li"
        },
        "chapter_id_selector": {
          "selector": "a",
          "attribute": "href"
        }
      },
      "chapter_by_id_selectors": {
        "main_selector": {
          "selector": " .manga-body > .read-manga > .read-content > img",
          "attribute": ""
        },
        "image_selector": {
          "selector": "this",
          "attribute": "data-src"
        },
        "title_selector": {
          "selector": "this",
          "attribute": "alt"
        },
        "id_selector": {
          "selector": "this",
          "attribute": "data-src"
        }
      },

      "content_selector": {
        "selector": ".manga-lists > .manga-item"
      }
    },
    "enabled": true
  },
  {
    "url": "https://kissmanga.in/",
    "searchUrl": "https://kissmanga.in/page/{page}/?s={search}&post_type=wp-manga&m_orderby=views",
    "type": "4",
    "decodeType": "1",
    "NSFW": "1",
    "getType": "1",
    "isPreview": "0",
    "isEmbed": "0",
    "name": "kissmanga",
    "icon": "https://dist-04est.imgcdn.co/wp-content/uploads/2020/01/picturetopeople.org-d1a4ac0eb1961d1168c973c8ee532aaf06950ff1b0b7d50b78.png",
    "pageType": "page",
    "query": {
      "latest": "mangalist/page/{page}/?m_orderby=latest",
      "rating": "mangalist/page/{page}/?m_orderby=rating",
      "trending": "mangalist/page/{page}/?m_orderby=trending",
      "most viewes": "mangalist/page/{page}/?m_orderby=views",
      "new manga": "mangalist/page/{page}/?m_orderby=new-manga"
    },
    "config": {
      "title_selector": {
        "selector": ".col-md-2 > .tab-thumb > a",
        "attribute": "title"
      },
      "thumbnail_selector": {
        "selector": ".col-md-2 > .tab-thumb > a > img",
        "attribute": "src"
      },
      "content_url_selector": {
        "selector": ".col-md-2 > .tab-thumb > a",
        "attribute": "href"
      },
      "detail_selector": {
        "selector": "html"
      },
      "detail": {
        "discription_selector": {
          "selector": "meta[name='description']",
          "attribute": "content"
        },
        "genre_selector": {
          "selector": ".post-status > .post-content_item:last-child > .summary-content"
        },
        "status_selector": {
          "selector": ".post-status > .post-content_item:last-child > .summary-content"
        },
        "chapter_name_selector": {
          "selector": "a"
        },
        "chapter_image_selector": {
          "selector": ""
        },
        "chapters_selector": {
          "selector": "#chapterlist > .row-content-chapter > li"
        },
        "chapter_id_selector": {
          "selector": "a",
          "attribute": "href"
        }
      },
      "chapter_by_id_selectors": {
        "main_selector": {
          "selector": " .manga-body > .read-manga > .read-content > img",
          "attribute": ""
        },
        "image_selector": {
          "selector": "this",
          "attribute": "data-src"
        },
        "title_selector": {
          "selector": "this",
          "attribute": "alt"
        },
        "id_selector": {
          "selector": "this",
          "attribute": "data-src"
        }
      },

      "content_selector": {
        "selector": ".tab-content-wrap > .c-tabs-item > .page-content-listin"
      }
    },
    "enabled": true
  }
]
